WrfPyApp/__init__.py
WrfPyApp-1.4.dist-info/LICENSE
WrfPyApp-1.4.dist-info/METADATA
WrfPyApp-1.4.dist-info/WHEEL
WrfPyApp-1.4.dist-info/top_level.txt
WrfPyApp-1.4.dist-info/RECORD
